easy_rl_env/__init__.py
easy_rl_env/base_env.py
easy_rl_env-0.1.0.dist-info/METADATA
easy_rl_env-0.1.0.dist-info/WHEEL
easy_rl_env-0.1.0.dist-info/top_level.txt
easy_rl_env-0.1.0.dist-info/RECORD
