Metadata-Version: 2.4
Name: easy-rl-env
Version: 0.1.0
Summary: Easily create custom RL environments for Gymnasium
Home-page: https://github.com/yourusername/easy-rl-env
Author: Your Name
Author-email: you@example.com
Requires-Python: >=3.7
Requires-Dist: numpy
Requires-Dist: gymnasium
Dynamic: author
Dynamic: author-email
Dynamic: description
Dynamic: description-content-type
Dynamic: home-page
Dynamic: requires-dist
Dynamic: requires-python
Dynamic: summary
